creampuff/__init__.py
creampuff-0.0.0.dist-info/WHEEL
creampuff-0.0.0.dist-info/METADATA
creampuff-0.0.0.dist-info/RECORD
